ensembl/brc4/__init__.py
ensembl/brc4/runnable/__init__.py
ensembl/brc4/runnable/compare_fasta.py
ensembl/brc4/runnable/compare_report.py
ensembl/brc4/runnable/fill_metadata.py
ensembl/brc4/runnable/json_schema_factory.py
ensembl/brc4/runnable/load_sequence_data.py
ensembl/brc4/runnable/prepare_genome.py
ensembl/brc4/runnable/seqregion_parser.py
ensembl/io/genomio/__init__.py
ensembl/io/genomio/annotation/__init__.py
ensembl/io/genomio/annotation/update_description.py
ensembl/io/genomio/assembly/__init__.py
ensembl/io/genomio/assembly/download.py
ensembl/io/genomio/assembly/status.py
ensembl/io/genomio/data/__init__.py
ensembl/io/genomio/data/external_db_map/__init__.py
ensembl/io/genomio/data/external_db_map/default.txt
ensembl/io/genomio/data/external_db_map/minimal.txt
ensembl/io/genomio/data/gff3/__init__.py
ensembl/io/genomio/data/gff3/biotypes.json
ensembl/io/genomio/data/schemas/__init__.py
ensembl/io/genomio/data/schemas/functional_annotation.json
ensembl/io/genomio/data/schemas/genome.json
ensembl/io/genomio/data/schemas/manifest.json
ensembl/io/genomio/data/schemas/seq_attrib.json
ensembl/io/genomio/data/schemas/seq_region.json
ensembl/io/genomio/database/__init__.py
ensembl/io/genomio/database/core_server.py
ensembl/io/genomio/database/dbconnection_lite.py
ensembl/io/genomio/database/factory.py
ensembl/io/genomio/database/meta_getter.py
ensembl/io/genomio/events/__init__.py
ensembl/io/genomio/events/dump.py
ensembl/io/genomio/events/format.py
ensembl/io/genomio/events/load.py
ensembl/io/genomio/external_db/__init__.py
ensembl/io/genomio/external_db/db_map.py
ensembl/io/genomio/fasta/__init__.py
ensembl/io/genomio/fasta/chunk.py
ensembl/io/genomio/fasta/process.py
ensembl/io/genomio/genbank/__init__.py
ensembl/io/genomio/genbank/download.py
ensembl/io/genomio/genbank/extract_data.py
ensembl/io/genomio/genome_metadata/__init__.py
ensembl/io/genomio/genome_metadata/dump.py
ensembl/io/genomio/genome_metadata/extend.py
ensembl_genomio-1.6.1.dist-info/LICENSE
ensembl_genomio-1.6.1.dist-info/METADATA
ensembl_genomio-1.6.1.dist-info/NOTICE
ensembl_genomio-1.6.1.dist-info/WHEEL
ensembl_genomio-1.6.1.dist-info/entry_points.txt
ensembl_genomio-1.6.1.dist-info/top_level.txt
ensembl_genomio-1.6.1.dist-info/RECORD
