Metadata-Version: 2.2
Name: ensembl-genomio
Version: 1.6.1
Summary: Ensembl GenomIO -- pipelines to convert basic genomic data into Ensembl cores and back to flatfile
Author-email: Ensembl <dev@ensembl.org>
License: Apache License 2.0
Project-URL: homepage, https://www.ensembl.org
Project-URL: repository, https://github.com/Ensembl/ensembl-genomio
Project-URL: documentation, https://ensembl.github.io/ensembl-genomio
Keywords: genome_io,ensembl,bioinformatics,annotation,setup
Classifier: Development Status :: 4 - Beta
Classifier: Environment :: Console
Classifier: Intended Audience :: Science/Research
Classifier: License :: OSI Approved :: Apache Software License
Classifier: Operating System :: OS Independent
Classifier: Programming Language :: Python
Classifier: Programming Language :: Python :: 3
Classifier: Programming Language :: Python :: 3 :: Only
Classifier: Programming Language :: Python :: 3.10
Classifier: Programming Language :: Python :: 3.11
Classifier: Topic :: Scientific/Engineering :: Bio-Informatics
Classifier: Topic :: Software Development :: Libraries :: Python Modules
Requires-Python: >=3.10
License-File: LICENSE
License-File: NOTICE
Requires-Dist: bcbio-gff==0.7.1
Requires-Dist: biopython>=1.81
Requires-Dist: ensembl-py>=2.1.2
Requires-Dist: ensembl-utils>=0.5.1
Requires-Dist: jsonschema>=4.6.0
Requires-Dist: intervaltree>=3.1.0
Requires-Dist: mysql-connector-python>=8.0.29
Requires-Dist: python-redmine>=2.3.0
Requires-Dist: requests>=2.28.0
Requires-Dist: spython>=0.3.13
Provides-Extra: build
Requires-Dist: build; extra == "build"
Requires-Dist: setuptools; extra == "build"
Requires-Dist: setuptools-scm; extra == "build"
Requires-Dist: wheel; extra == "build"
Provides-Extra: cicd
Requires-Dist: black>=23.11.0; extra == "cicd"
Requires-Dist: coverage>=7.3.2; extra == "cicd"
Requires-Dist: deepdiff>=6.7.1; extra == "cicd"
Requires-Dist: genbadge[coverage]; extra == "cicd"
Requires-Dist: mypy>=1.2.0; extra == "cicd"
Requires-Dist: pylint>=3.0.2; extra == "cicd"
Requires-Dist: pytest>=7.4.3; extra == "cicd"
Requires-Dist: pytest-dependency; extra == "cicd"
Requires-Dist: pytest-mock; extra == "cicd"
Requires-Dist: pytest-workflow>=2.1.0; extra == "cicd"
Requires-Dist: types-requests; extra == "cicd"
Provides-Extra: docs
Requires-Dist: mkdocs>=1.5.3; extra == "docs"
Requires-Dist: mkdocs-autorefs; extra == "docs"
Requires-Dist: mkdocs-gen-files; extra == "docs"
Requires-Dist: mkdocs-literate-nav; extra == "docs"
Requires-Dist: mkdocs-material; extra == "docs"
Requires-Dist: mkdocs-material-extensions; extra == "docs"
Requires-Dist: mkdocs-section-index; extra == "docs"
Requires-Dist: mkdocstrings; extra == "docs"
Requires-Dist: mkdocstrings-python; extra == "docs"
Provides-Extra: mysql
Requires-Dist: ensembl-utils[mysql]; extra == "mysql"
